cloudstile/__init__.py
cloudstile/asyncturnstile.py
cloudstile/base.py
cloudstile/models/__init__.py
cloudstile/models/response.py
cloudstile/syncturnstile.py
cloudstile-2.0.1.dist-info/LICENSE
cloudstile-2.0.1.dist-info/METADATA
cloudstile-2.0.1.dist-info/WHEEL
cloudstile-2.0.1.dist-info/RECORD
