Metadata-Version: 2.3
Name: cloudstile
Version: 2.0.1
Summary: Unofficial Cloudflare Turnstile library for Python with async and sync support.
License: MIT
Keywords: cloudflare,turnstile,captcha
Author: NotAussie
Author-email: notaussie@duck.com
Requires-Python: >=3.9,<4.0
Classifier: Framework :: Pydantic
Classifier: Intended Audience :: Developers
Classifier: License :: OSI Approved :: MIT License
Classifier: Operating System :: OS Independent
Classifier: Programming Language :: Python :: 3
Classifier: Programming Language :: Python :: 3.9
Classifier: Programming Language :: Python :: 3.10
Classifier: Programming Language :: Python :: 3.11
Classifier: Programming Language :: Python :: 3.12
Classifier: Programming Language :: Python :: 3.13
Classifier: Topic :: Security
Classifier: Topic :: Software Development :: Libraries :: Python Modules
Requires-Dist: httpx (==0.28.1)
Requires-Dist: pydantic (==2.11.7)
Requires-Dist: typing-extensions (==4.14.1)
Project-URL: Repository, https://github.com/notaussie/cloudstile
